dverse_nats_helper/__init__.py
dverse_nats_helper/event_builder.py
dverse_nats_helper/event_schema.py
dverse_nats_helper/example_models.py
dverse_nats_helper/nats_connection.py
dverse_nats_helper-0.2.0.dist-info/METADATA
dverse_nats_helper-0.2.0.dist-info/WHEEL
dverse_nats_helper-0.2.0.dist-info/licenses/LICENSE
dverse_nats_helper-0.2.0.dist-info/RECORD
