Metadata-Version: 2.4
Name: dverse-nats-helper
Version: 0.2.0
Summary: A Python library for NATS server connection, publishing, creation, and validation of events.
Project-URL: Homepage, https://github.com/fuas-dverse/dverse-nats-helper
Project-URL: Issues, https://github.com/fuas-dverse/dverse-nats-helper/issues
Author-email: aniakowalewska <466069@student.fontys.nl>
License-File: LICENSE
Classifier: License :: OSI Approved :: MIT License
Classifier: Operating System :: OS Independent
Classifier: Programming Language :: Python :: 3
Requires-Python: >=3.8
